ingit/__init__.py
ingit/__main__.py
ingit/_version.py
ingit/action_progress.py
ingit/fetch_flags.py
ingit/json_config.py
ingit/main.py
ingit/project.py
ingit/push_flags.py
ingit/py.typed
ingit/repo_data.py
ingit/runtime.py
ingit/runtime_interface.py
ingit-0.5.1.dist-info/licenses/LICENSE
ingit-0.5.1.dist-info/licenses/NOTICE
ingit-0.5.1.dist-info/METADATA
ingit-0.5.1.dist-info/WHEEL
ingit-0.5.1.dist-info/entry_points.txt
ingit-0.5.1.dist-info/top_level.txt
ingit-0.5.1.dist-info/RECORD
