Metadata-Version: 2.4
Name: ingit
Version: 0.5.1
Summary: Tool for managing a large collection of repositories in git.
Home-page: https://github.com/mbdevpl/ingit
Download-URL: 
Author: Mateusz Bysiek
Author-email: mateusz.bysiek@gmail.com
Maintainer: Mateusz Bysiek
Maintainer-email: mateusz.bysiek@gmail.com
License-Expression: GPL-3.0-or-later
Keywords: tools,vcs,repository management,git,submodules
Classifier: Development Status :: 4 - Beta
Classifier: Environment :: Console
Classifier: Intended Audience :: Developers
Classifier: Intended Audience :: System Administrators
Classifier: Natural Language :: English
Classifier: Operating System :: MacOS
Classifier: Operating System :: Microsoft :: Windows
Classifier: Operating System :: POSIX :: Linux
Classifier: Programming Language :: Python :: 3.10
Classifier: Programming Language :: Python :: 3.11
Classifier: Programming Language :: Python :: 3.12
Classifier: Programming Language :: Python :: 3.13
Classifier: Programming Language :: Python :: 3 :: Only
Classifier: Topic :: Software Development :: Version Control
Classifier: Topic :: Software Development :: Version Control :: Git
Classifier: Topic :: System :: Archiving :: Backup
Classifier: Topic :: System :: Archiving :: Mirroring
Classifier: Topic :: System :: Monitoring
Classifier: Topic :: Utilities
Classifier: Typing :: Typed
Requires-Python: >=3.10
License-File: LICENSE
License-File: NOTICE
Requires-Dist: argcomplete~=3.0
Requires-Dist: boilerplates[cli,config,logging]~=1.2
Requires-Dist: GitPython~=3.1
Requires-Dist: ordered-set~=4.1
Requires-Dist: readchar~=4.0
Requires-Dist: version-query~=1.5
Dynamic: author
Dynamic: author-email
Dynamic: classifier
Dynamic: description
Dynamic: description-content-type
Dynamic: home-page
Dynamic: keywords
Dynamic: license-file
Dynamic: license-expression
Dynamic: maintainer
Dynamic: maintainer-email
Dynamic: requires-dist
Dynamic: requires-python
Dynamic: summary
